{"assets/ICONS.png":["assets/ICONS.png"],"assets/account_icon.png":["assets/account_icon.png"],"assets/audio_image.jpg":["assets/audio_image.jpg"],"assets/home_icon.png":["assets/home_icon.png"],"assets/images/GUIDE_amelia.png":["assets/images/GUIDE_amelia.png"],"assets/images/GUIDE_christopher.png":["assets/images/GUIDE_christopher.png"],"assets/images/GUIDE_jenny.png":["assets/images/GUIDE_jenny.png"],"assets/images/GUIDE_ryan.png":["assets/images/GUIDE_ryan.png"],"assets/images/ICONS.ai":["assets/images/ICONS.ai"],"assets/images/background_animated.gif":["assets/images/background_animated.gif"],"assets/images/starbackground_video.mp4":["assets/images/starbackground_video.mp4"],"assets/images/starbackground_video1.mp4":["assets/images/starbackground_video1.mp4"],"assets/music/Space_[music_background_audio_file].mp3":["assets/music/Space_[music_background_audio_file].mp3"],"assets/music/purpose/Be Happy.mp3":["assets/music/purpose/Be Happy.mp3"],"assets/music/purpose/Focus.mp3":["assets/music/purpose/Focus.mp3"],"assets/music/purpose/Sleepbetter.mp3":["assets/music/purpose/Sleepbetter.mp3"],"assets/music/ryan_english.txt":["assets/music/ryan_english.txt"],"assets/music/sound/Hiphop.mp3":["assets/music/sound/Hiphop.mp3"],"assets/music/sound/Space.mp3":["assets/music/sound/Space.mp3"],"assets/music/sound/Techno.mp3":["assets/music/sound/Techno.mp3"],"assets/mybreathwork_colors_001.pdf":["assets/mybreathwork_colors_001.pdf"],"assets/mybreathwork_logo_001.pdf":["assets/mybreathwork_logo_001.pdf"],"assets/mybreathwork_logo_001.png":["assets/mybreathwork_logo_001.png"],"assets/sub_messages.xlsx":["assets/sub_messages.xlsx"],"packages/cupertino_icons/assets/CupertinoIcons.ttf":["packages/cupertino_icons/assets/CupertinoIcons.ttf"]}